<apps version="2.0">
  <app keywords="ece353" req_capabilities_v2="[ece353-bsp,cy8ckit_062s4]">
    <name>ECE 353 - Getting Started</name>
    <id>ece353-mtb-init-app</id>
    <category>ECE 353</category>
    <uri>https://git.doit.wisc.edu/engr/ece/cmpe_courses/ece-353-public-share/ece353-mtb-init-app</uri>
    <description><![CDATA[This is the starter project for the ECE 353 - Introduction to Microprocessor Systems]]></description>
    <req_capabilities>psoc6</req_capabilities>
    <versions>
      <version flow_version="2.0" tools_min_version="2.4.0" tools_max_version="2.4.1" req_capabilities_per_version="bsp_gen3">
        <num>Latest release</num>
        <commit>main</commit>
      </version>
    </versions>
  </app>
</apps>